Workbook

Sheet Gastos
A1: Fecha | B1: Proveedor | C1: Concepto | D1: Categoría | E1: Importe (EUR) | F1: Importe original | G1: Moneda | H1: Recurrente? | I1: Cuenta email | J1: Recibo
A2: 46121 | B2: Google | C2: Play Console - Developer Registration Fee | D2: App Stores | E2: 23 | F2: 25 | G2: USD | H2: No | I2: cals2gains@gmail.com | J2: PDS.9797-3611-4976-86649
A3: 46122 | B3: Apple | C3: iCloud+ 2TB (Mensual) | D3: IA/Suscripciones | E3: 9.99 | F3: 9.99 | G3: EUR | H3: Sí | I3: judith.cordobes@gmail.com | J3: Seq: 1-13376832551
A4: 46125 | B4: Apple/Meta | C4: Meta Verified For Business (Instagram) | D4: Publicidad | E4: 16.99 | F4: 16.99 | G4: EUR | H4: Sí | I4: judith.cordobes@gmail.com | J4: Seq: 1-13389522137
D5: TOTAL | E5: =SUM(E2:E4)

Sheet Resumen Mensual
A1: Mes | B1: IA/Suscripciones | C1: App Stores | D1: Publicidad | E1: Hosting/Dominio | F1: Herramientas | G1: Otros | H1: TOTAL MES
A2: Abril 2026 | B2: 9.99 | C2: 23 | D2: 16.99 | E2: 0 | F2: 0 | G2: 0 | H2: =SUM(B2:G2)
A3: Mayo 2026 | B3: 0 | C3: 0 | D3: 0 | E3: 0 | F3: 0 | G3: 0 | H3: =SUM(B3:G3)
A4: Junio 2026 | B4: 0 | C4: 0 | D4: 0 | E4: 0 | F4: 0 | G4: 0 | H4: =SUM(B4:G4)
A5: Julio 2026 | B5: 0 | C5: 0 | D5: 0 | E5: 0 | F5: 0 | G5: 0 | H5: =SUM(B5:G5)
A6: Agosto 2026 | B6: 0 | C6: 0 | D6: 0 | E6: 0 | F6: 0 | G6: 0 | H6: =SUM(B6:G6)
A7: Septiembre 2026 | B7: 0 | C7: 0 | D7: 0 | E7: 0 | F7: 0 | G7: 0 | H7: =SUM(B7:G7)
A8: Octubre 2026 | B8: 0 | C8: 0 | D8: 0 | E8: 0 | F8: 0 | G8: 0 | H8: =SUM(B8:G8)
A9: Noviembre 2026 | B9: 0 | C9: 0 | D9: 0 | E9: 0 | F9: 0 | G9: 0 | H9: =SUM(B9:G9)
A10: Diciembre 2026 | B10: 0 | C10: 0 | D10: 0 | E10: 0 | F10: 0 | G10: 0 | H10: =SUM(B10:G10)
A11: TOTAL ACUMULADO | B11: =SUM(B2:B10) | C11: =SUM(C2:C10) | D11: =SUM(D2:D10) | E11: =SUM(E2:E10) | F11: =SUM(F2:F10) | G11: =SUM(G2:G10) | H11: =SUM(H2:H10)

Sheet Suscripciones
A1: Servicio | B1: Plan | C1: Coste mensual (EUR) | D1: Coste anual (EUR) | E1: Fecha inicio | F1: Próximo cobro | G1: Estado | H1: Cuenta
A2: iCloud+ | B2: 2 TB Mensual | C2: 9.99 | D2: =C2*12 | E2: 46122 | F2: 46148 | G2: Activa | H2: judith.cordobes@gmail.com
A3: Meta Verified For Business | B3: Instagram (Mensual) | C3: 16.99 | D3: =C3*12 | E3: 46124 | F3: 46154 | G3: Activa | H3: judith.cordobes@gmail.com
A4: Claude (Anthropic) | B4: Pro (estimado) | C4: 20 | D4: =C4*12 | G4: Por confirmar | H4: info@civiltek.es
A5: ChatGPT (OpenAI) | B5: Plus (estimado) | C5: 20 | D5: =C5*12 | G5: Por confirmar | H5: —
A6: Google Workspace | B6: Business Starter | C6: 6 | D6: =C6*12 | G6: Por confirmar | H6: info@civiltek.es
A7: Apple Developer Program | B7: Anual | C7: =D7/12 | D7: 99 | E7: 46122 | F7: 46487 | G7: Pendiente pago | H7: judith.cordobes@gmail.com
A8: Expo (EAS) | B8: Free / Production | C8: 0 | D8: 0 | G8: Por confirmar | H8: cals2gains@gmail.com
A9: Dominio (Doominio) | B9: cals2gains.com | G9: Por confirmar | H9: —
B10: TOTAL MENSUAL | C10: =SUM(C2:C9) | D10: =SUM(D2:D9)

Sheet Publicidad
A1: Fecha | B1: Plataforma | C1: Campaña | D1: Gasto (EUR) | E1: Impresiones | F1: Clicks | G1: Conversiones | H1: CPA (EUR) | I1: ROAS
A2: (datos cuando lancemos campañas)

Sheet Ingresos
A1: Fecha | B1: Plataforma | C1: Concepto | D1: Importe bruto (EUR) | E1: Comisión store (EUR) | F1: Impuestos (EUR) | G1: Neto (EUR)
A2: (datos cuando la app genere ingresos)

Sheet P&L
A1: Concepto | B1: Abril 2026 | C1: Mayo 2026 | D1: Junio 2026 | E1: Julio 2026 | F1: Agosto 2026 | G1: Septiembre 2026 | H1: Octubre 2026 | I1: Noviembre 2026 | J1: Diciembre 2026
A2: INGRESOS
A3: Suscripciones App
A4: In-App Purchases
A5: Publicidad in-app
A6: Total Ingresos | B6: =SUM(B3:B5)
A8: GASTOS
A9: IA/Suscripciones | B9: ='Resumen Mensual'!B2
A10: App Stores | B10: ='Resumen Mensual'!C2
A11: Publicidad | B11: ='Resumen Mensual'!D2
A12: Hosting/Dominio
A13: Herramientas
A14: Otros
A15: Total Gastos | B15: =SUM(B9:B14)
A17: RESULTADO NETO | B17: =B6-B15
A18: Margen (%)
A19: Burn Rate (EUR/mes)

Sheet Métricas vs Gasto
A1: Mes | B1: Gasto publicidad (EUR) | C1: Nuevos usuarios | D1: CAC (EUR) | E1: LTV estimado (EUR) | F1: ROI (%)
A2: Abril 2026 | D2: =IF(C2>0,B2/C2,0) | F2: =IF(B2>0,(E2*C2-B2)/B2,0)
A3: Mayo 2026 | D3: =IF(C3>0,B3/C3,0) | F3: =IF(B3>0,(E3*C3-B3)/B3,0)
A4: Junio 2026 | D4: =IF(C4>0,B4/C4,0) | F4: =IF(B4>0,(E4*C4-B4)/B4,0)
A5: Julio 2026 | D5: =IF(C5>0,B5/C5,0) | F5: =IF(B5>0,(E5*C5-B5)/B5,0)
A6: Agosto 2026 | D6: =IF(C6>0,B6/C6,0) | F6: =IF(B6>0,(E6*C6-B6)/B6,0)
A7: Septiembre 2026 | D7: =IF(C7>0,B7/C7,0) | F7: =IF(B7>0,(E7*C7-B7)/B7,0)
A8: Octubre 2026 | D8: =IF(C8>0,B8/C8,0) | F8: =IF(B8>0,(E8*C8-B8)/B8,0)
A9: Noviembre 2026 | D9: =IF(C9>0,B9/C9,0) | F9: =IF(B9>0,(E9*C9-B9)/B9,0)
A10: Diciembre 2026 | D10: =IF(C10>0,B10/C10,0) | F10: =IF(B10>0,(E10*C10-B10)/B10,0)

Sheet Dashboard
A1: CALS2GAINS — Dashboard Financiero
A3: Gasto Total Acumulado | C3: Burn Rate Mensual | E3: Suscripciones Activas | G3: Ingresos Totales
A4: ='Resumen Mensual'!H11 | C4: ='Resumen Mensual'!H2 | E4: 2 | G4: 0
A6: Categoría | B6: Gasto Abril (EUR)
A7: IA/Suscripciones | B7: ='Resumen Mensual'!B2
A8: App Stores | B8: ='Resumen Mensual'!C2
A9: Publicidad | B9: ='Resumen Mensual'!D2
A10: Hosting/Dominio | B10: 0
A11: Herramientas | B11: 0
A12: Otros | B12: 0
